spagim/GenesMetrics.py
spagim/__init__.py
spagim/benchmark.py
spagim/dimensionality_reduction.py
spagim/main.py
spagim/principal_vectors.py
spagim-1.0.2.dist-info/METADATA
spagim-1.0.2.dist-info/WHEEL
spagim-1.0.2.dist-info/top_level.txt
spagim-1.0.2.dist-info/RECORD
